files/__init__.py
files/operations.py
working_ujson-0.0.1.dist-info/METADATA
working_ujson-0.0.1.dist-info/WHEEL
working_ujson-0.0.1.dist-info/top_level.txt
working_ujson-0.0.1.dist-info/RECORD
