Metadata-Version: 2.1
Name: working-ujson
Version: 0.0.1
Summary: Working with file package
Requires: ujson
Requires-Python: >=3.11
